.gitlab-ci.yml
CHANGELOG.md
README.md
README.rst
__init__.py
description.txt
setup.py
.git/FETCH_HEAD
.git/HEAD
.git/config
.git/index
.git/shallow
.git/logs/HEAD
.git/logs/refs/remotes/origin/main
.git/objects/pack/pack-5fcb7a4a337d5d4bbbca347cce81b18d6bbbee03.idx
.git/objects/pack/pack-5fcb7a4a337d5d4bbbca347cce81b18d6bbbee03.pack
.git/refs/pipelines/754287681
.git/refs/remotes/origin/main
.git/refs/tags/0.0.10
.git/refs/tags/1.1.0
.git/refs/tags/1.1.1
.git/refs/tags/1.1.3
.git/refs/tags/1.2.0
.git/refs/tags/1.3.0
.git/refs/tags/1.3.1
.git/refs/tags/1.4.0
openapi_django/__init__.py
openapi_django/admin.py
openapi_django/apps.py
openapi_django/models.py
openapi_django/tests.py
openapi_django/urls.py
openapi_django/views.py
openapi_django/migrations/__init__.py
openapi_django/openapi_utils/__init__.py
openapi_django/openapi_utils/collectors.py
openapi_django/openapi_utils/decorators.py
openapi_django/openapi_utils/objects.py
openapi_django-1.4.1.dist-info/METADATA
openapi_django-1.4.1.dist-info/WHEEL
openapi_django-1.4.1.dist-info/top_level.txt
openapi_django-1.4.1.dist-info/RECORD
