Metadata-Version: 2.1
Name: openapi-django
Version: 1.4.1
Summary: OpenApi for django
Home-page: https://gitlab.com/kappasama.ks/openapi_django
Author: Y. Chudakov
Author-email: kappasama.ks@gmail.com
Requires-Dist: Django (>=3.2.6)
Requires-Dist: djantic (==0.7.0)
Requires-Dist: pydantic (==1.9.1)
